<?xml version="1.0" ?>
<Skill>
    <Levels>
        <Level>
            <Time>111</Time>
            <MP>6</MP>
            <HP>0</HP>
            <Item>0</Item>
            <ItemCount>0</ItemCount>
            <X>11</X>
            <Y>0</Y>
            <Speed>0</Speed>
            <Jump>0</Jump>
            <WAtk>0</WAtk>
            <WDef>0</WDef>
            <MAtk>0</MAtk>
            <MDef>0</MDef>
            <Acc>0</Acc>
            <Avo>0</Avo>
            <HPP>0</HPP>
        </Level>
        <Level>
            <Time>132</Time>
            <MP>6</MP>
            <HP>0</HP>
            <Item>0</Item>
            <ItemCount>0</ItemCount>
            <X>14</X>
            <Y>0</Y>
            <Speed>0</Speed>
            <Jump>0</Jump>
            <WAtk>0</WAtk>
            <WDef>0</WDef>
            <MAtk>0</MAtk>
            <MDef>0</MDef>
            <Acc>0</Acc>
            <Avo>0</Avo>
            <HPP>0</HPP>
        </Level>
        <Level>
            <Time>153</Time>
            <MP>6</MP>
            <HP>0</HP>
            <Item>0</Item>
            <ItemCount>0</ItemCount>
            <X>17</X>
            <Y>0</Y>
            <Speed>0</Speed>
            <Jump>0</Jump>
            <WAtk>0</WAtk>
            <WDef>0</WDef>
            <MAtk>0</MAtk>
            <MDef>0</MDef>
            <Acc>0</Acc>
            <Avo>0</Avo>
            <HPP>0</HPP>
        </Level>
        <Level>
            <Time>174</Time>
            <MP>6</MP>
            <HP>0</HP>
            <Item>0</Item>
            <ItemCount>0</ItemCount>
            <X>20</X>
            <Y>0</Y>
            <Speed>0</Speed>
            <Jump>0</Jump>
            <WAtk>0</WAtk>
            <WDef>0</WDef>
            <MAtk>0</MAtk>
            <MDef>0</MDef>
            <Acc>0</Acc>
            <Avo>0</Avo>
            <HPP>0</HPP>
        </Level>
        <Level>
            <Time>195</Time>
            <MP>6</MP>
            <HP>0</HP>
            <Item>0</Item>
            <ItemCount>0</ItemCount>
            <X>23</X>
            <Y>0</Y>
            <Speed>0</Speed>
            <Jump>0</Jump>
            <WAtk>0</WAtk>
            <WDef>0</WDef>
            <MAtk>0</MAtk>
            <MDef>0</MDef>
            <Acc>0</Acc>
            <Avo>0</Avo>
            <HPP>0</HPP>
        </Level>
        <Level>
            <Time>246</Time>
            <MP>8</MP>
            <HP>0</HP>
            <Item>0</Item>
            <ItemCount>0</ItemCount>
            <X>30</X>
            <Y>0</Y>
            <Speed>0</Speed>
            <Jump>0</Jump>
            <WAtk>0</WAtk>
            <WDef>0</WDef>
            <MAtk>0</MAtk>
            <MDef>0</MDef>
            <Acc>0</Acc>
            <Avo>0</Avo>
            <HPP>0</HPP>
        </Level>
        <Level>
            <Time>267</Time>
            <MP>8</MP>
            <HP>0</HP>
            <Item>0</Item>
            <ItemCount>0</ItemCount>
            <X>33</X>
            <Y>0</Y>
            <Speed>0</Speed>
            <Jump>0</Jump>
            <WAtk>0</WAtk>
            <WDef>0</WDef>
            <MAtk>0</MAtk>
            <MDef>0</MDef>
            <Acc>0</Acc>
            <Avo>0</Avo>
            <HPP>0</HPP>
        </Level>
        <Level>
            <Time>288</Time>
            <MP>8</MP>
            <HP>0</HP>
            <Item>0</Item>
            <ItemCount>0</ItemCount>
            <X>36</X>
            <Y>0</Y>
            <Speed>0</Speed>
            <Jump>0</Jump>
            <WAtk>0</WAtk>
            <WDef>0</WDef>
            <MAtk>0</MAtk>
            <MDef>0</MDef>
            <Acc>0</Acc>
            <Avo>0</Avo>
            <HPP>0</HPP>
        </Level>
        <Level>
            <Time>309</Time>
            <MP>8</MP>
            <HP>0</HP>
            <Item>0</Item>
            <ItemCount>0</ItemCount>
            <X>39</X>
            <Y>0</Y>
            <Speed>0</Speed>
            <Jump>0</Jump>
            <WAtk>0</WAtk>
            <WDef>0</WDef>
            <MAtk>0</MAtk>
            <MDef>0</MDef>
            <Acc>0</Acc>
            <Avo>0</Avo>
            <HPP>0</HPP>
        </Level>
        <Level>
            <Time>330</Time>
            <MP>8</MP>
            <HP>0</HP>
            <Item>0</Item>
            <ItemCount>0</ItemCount>
            <X>42</X>
            <Y>0</Y>
            <Speed>0</Speed>
            <Jump>0</Jump>
            <WAtk>0</WAtk>
            <WDef>0</WDef>
            <MAtk>0</MAtk>
            <MDef>0</MDef>
            <Acc>0</Acc>
            <Avo>0</Avo>
            <HPP>0</HPP>
        </Level>
        <Level>
            <Time>381</Time>
            <MP>10</MP>
            <HP>0</HP>
            <Item>0</Item>
            <ItemCount>0</ItemCount>
            <X>49</X>
            <Y>0</Y>
            <Speed>0</Speed>
            <Jump>0</Jump>
            <WAtk>0</WAtk>
            <WDef>0</WDef>
            <MAtk>0</MAtk>
            <MDef>0</MDef>
            <Acc>0</Acc>
            <Avo>0</Avo>
            <HPP>0</HPP>
        </Level>
        <Level>
            <Time>402</Time>
            <MP>10</MP>
            <HP>0</HP>
            <Item>0</Item>
            <ItemCount>0</ItemCount>
            <X>52</X>
            <Y>0</Y>
            <Speed>0</Speed>
            <Jump>0</Jump>
            <WAtk>0</WAtk>
            <WDef>0</WDef>
            <MAtk>0</MAtk>
            <MDef>0</MDef>
            <Acc>0</Acc>
            <Avo>0</Avo>
            <HPP>0</HPP>
        </Level>
        <Level>
            <Time>423</Time>
            <MP>10</MP>
            <HP>0</HP>
            <Item>0</Item>
            <ItemCount>0</ItemCount>
            <X>55</X>
            <Y>0</Y>
            <Speed>0</Speed>
            <Jump>0</Jump>
            <WAtk>0</WAtk>
            <WDef>0</WDef>
            <MAtk>0</MAtk>
            <MDef>0</MDef>
            <Acc>0</Acc>
            <Avo>0</Avo>
            <HPP>0</HPP>
        </Level>
        <Level>
            <Time>444</Time>
            <MP>10</MP>
            <HP>0</HP>
            <Item>0</Item>
            <ItemCount>0</ItemCount>
            <X>58</X>
            <Y>0</Y>
            <Speed>0</Speed>
            <Jump>0</Jump>
            <WAtk>0</WAtk>
            <WDef>0</WDef>
            <MAtk>0</MAtk>
            <MDef>0</MDef>
            <Acc>0</Acc>
            <Avo>0</Avo>
            <HPP>0</HPP>
        </Level>
        <Level>
            <Time>465</Time>
            <MP>10</MP>
            <HP>0</HP>
            <Item>0</Item>
            <ItemCount>0</ItemCount>
            <X>61</X>
            <Y>0</Y>
            <Speed>0</Speed>
            <Jump>0</Jump>
            <WAtk>0</WAtk>
            <WDef>0</WDef>
            <MAtk>0</MAtk>
            <MDef>0</MDef>
            <Acc>0</Acc>
            <Avo>0</Avo>
            <HPP>0</HPP>
        </Level>
        <Level>
            <Time>516</Time>
            <MP>12</MP>
            <HP>0</HP>
            <Item>0</Item>
            <ItemCount>0</ItemCount>
            <X>68</X>
            <Y>0</Y>
            <Speed>0</Speed>
            <Jump>0</Jump>
            <WAtk>0</WAtk>
            <WDef>0</WDef>
            <MAtk>0</MAtk>
            <MDef>0</MDef>
            <Acc>0</Acc>
            <Avo>0</Avo>
            <HPP>0</HPP>
        </Level>
        <Level>
            <Time>537</Time>
            <MP>12</MP>
            <HP>0</HP>
            <Item>0</Item>
            <ItemCount>0</ItemCount>
            <X>71</X>
            <Y>0</Y>
            <Speed>0</Speed>
            <Jump>0</Jump>
            <WAtk>0</WAtk>
            <WDef>0</WDef>
            <MAtk>0</MAtk>
            <MDef>0</MDef>
            <Acc>0</Acc>
            <Avo>0</Avo>
            <HPP>0</HPP>
        </Level>
        <Level>
            <Time>558</Time>
            <MP>12</MP>
            <HP>0</HP>
            <Item>0</Item>
            <ItemCount>0</ItemCount>
            <X>74</X>
            <Y>0</Y>
            <Speed>0</Speed>
            <Jump>0</Jump>
            <WAtk>0</WAtk>
            <WDef>0</WDef>
            <MAtk>0</MAtk>
            <MDef>0</MDef>
            <Acc>0</Acc>
            <Avo>0</Avo>
            <HPP>0</HPP>
        </Level>
        <Level>
            <Time>579</Time>
            <MP>12</MP>
            <HP>0</HP>
            <Item>0</Item>
            <ItemCount>0</ItemCount>
            <X>77</X>
            <Y>0</Y>
            <Speed>0</Speed>
            <Jump>0</Jump>
            <WAtk>0</WAtk>
            <WDef>0</WDef>
            <MAtk>0</MAtk>
            <MDef>0</MDef>
            <Acc>0</Acc>
            <Avo>0</Avo>
            <HPP>0</HPP>
        </Level>
        <Level>
            <Time>600</Time>
            <MP>12</MP>
            <HP>0</HP>
            <Item>0</Item>
            <ItemCount>0</ItemCount>
            <X>80</X>
            <Y>0</Y>
            <Speed>0</Speed>
            <Jump>0</Jump>
            <WAtk>0</WAtk>
            <WDef>0</WDef>
            <MAtk>0</MAtk>
            <MDef>0</MDef>
            <Acc>0</Acc>
            <Avo>0</Avo>
            <HPP>0</HPP>
        </Level>
    </Levels>
</Skill>
