<?xml version="1.0" ?>
<Map>
    <returnMap>211000000</returnMap>
    <NPCs />
    <Mobs />
    <Portals>
        <Portal>
            <id>0</id>
            <from>sp</from>
            <to></to>
            <toid>999999999</toid>
            <type>0</type>
            <x>-353</x>
            <y>-288</y>
        </Portal>
        <Portal>
            <id>1</id>
            <from>out00</from>
            <to>in00</to>
            <toid>211042200</toid>
            <type>2</type>
            <x>-291</x>
            <y>-244</y>
        </Portal>
    </Portals>
    <Footholds>
        <Foothold>
            <x1>-1335</x1>
            <y1>-150</y1>
            <x2>-1335</x2>
            <y2>-210</y2>
        </Foothold>
        <Foothold>
            <x1>-729</x1>
            <y1>-62</y1>
            <x2>-722</x2>
            <y2>-66</y2>
        </Foothold>
        <Foothold>
            <x1>-722</x1>
            <y1>-66</y1>
            <x2>-707</x2>
            <y2>-66</y2>
        </Foothold>
        <Foothold>
            <x1>-707</x1>
            <y1>-66</y1>
            <x2>-699</x2>
            <y2>-62</y2>
        </Foothold>
        <Foothold>
            <x1>-699</x1>
            <y1>-62</y1>
            <x2>-692</x2>
            <y2>-62</y2>
        </Foothold>
        <Foothold>
            <x1>-692</x1>
            <y1>-62</y1>
            <x2>-686</x2>
            <y2>-65</y2>
        </Foothold>
        <Foothold>
            <x1>-686</x1>
            <y1>-65</y1>
            <x2>-680</x2>
            <y2>-64</y2>
        </Foothold>
        <Foothold>
            <x1>-680</x1>
            <y1>-64</y1>
            <x2>-675</x2>
            <y2>-60</y2>
        </Foothold>
        <Foothold>
            <x1>-1215</x1>
            <y1>-240</y1>
            <x2>-1207</x2>
            <y2>-243</y2>
        </Foothold>
        <Foothold>
            <x1>-1207</x1>
            <y1>-243</y1>
            <x2>-1197</x2>
            <y2>-242</y2>
        </Foothold>
        <Foothold>
            <x1>-1197</x1>
            <y1>-242</y1>
            <x2>-1192</x2>
            <y2>-240</y2>
        </Foothold>
        <Foothold>
            <x1>-1192</x1>
            <y1>-240</y1>
            <x2>-1184</x2>
            <y2>-243</y2>
        </Foothold>
        <Foothold>
            <x1>-1184</x1>
            <y1>-243</y1>
            <x2>-1161</x2>
            <y2>-242</y2>
        </Foothold>
        <Foothold>
            <x1>-1161</x1>
            <y1>-242</y1>
            <x2>-1155</x2>
            <y2>-240</y2>
        </Foothold>
        <Foothold>
            <x1>-1155</x1>
            <y1>-240</y1>
            <x2>-1143</x2>
            <y2>-240</y2>
        </Foothold>
        <Foothold>
            <x1>-1143</x1>
            <y1>-240</y1>
            <x2>-1138</x2>
            <y2>-242</y2>
        </Foothold>
        <Foothold>
            <x1>-1138</x1>
            <y1>-242</y1>
            <x2>-1131</x2>
            <y2>-243</y2>
        </Foothold>
        <Foothold>
            <x1>-1131</x1>
            <y1>-243</y1>
            <x2>-1125</x2>
            <y2>-240</y2>
        </Foothold>
        <Foothold>
            <x1>-405</x1>
            <y1>-240</y1>
            <x2>-398</x2>
            <y2>-244</y2>
        </Foothold>
        <Foothold>
            <x1>-398</x1>
            <y1>-244</y1>
            <x2>-385</x2>
            <y2>-245</y2>
        </Foothold>
        <Foothold>
            <x1>-385</x1>
            <y1>-245</y1>
            <x2>-370</x2>
            <y2>-245</y2>
        </Foothold>
        <Foothold>
            <x1>-370</x1>
            <y1>-245</y1>
            <x2>-365</x2>
            <y2>-247</y2>
        </Foothold>
        <Foothold>
            <x1>-365</x1>
            <y1>-247</y1>
            <x2>-354</x2>
            <y2>-248</y2>
        </Foothold>
        <Foothold>
            <x1>-354</x1>
            <y1>-248</y1>
            <x2>-340</x2>
            <y2>-243</y2>
        </Foothold>
        <Foothold>
            <x1>-340</x1>
            <y1>-243</y1>
            <x2>-329</x2>
            <y2>-243</y2>
        </Foothold>
        <Foothold>
            <x1>-329</x1>
            <y1>-243</y1>
            <x2>-324</x2>
            <y2>-244</y2>
        </Foothold>
        <Foothold>
            <x1>-324</x1>
            <y1>-244</y1>
            <x2>-315</x2>
            <y2>-240</y2>
        </Foothold>
        <Foothold>
            <x1>-1305</x1>
            <y1>-240</y1>
            <x2>-1297</x2>
            <y2>-243</y2>
        </Foothold>
        <Foothold>
            <x1>-1297</x1>
            <y1>-243</y1>
            <x2>-1286</x2>
            <y2>-243</y2>
        </Foothold>
        <Foothold>
            <x1>-1286</x1>
            <y1>-243</y1>
            <x2>-1276</x2>
            <y2>-247</y2>
        </Foothold>
        <Foothold>
            <x1>-1276</x1>
            <y1>-247</y1>
            <x2>-1267</x2>
            <y2>-247</y2>
        </Foothold>
        <Foothold>
            <x1>-1267</x1>
            <y1>-247</y1>
            <x2>-1258</x2>
            <y2>-243</y2>
        </Foothold>
        <Foothold>
            <x1>-1258</x1>
            <y1>-243</y1>
            <x2>-1248</x2>
            <y2>-245</y2>
        </Foothold>
        <Foothold>
            <x1>-1248</x1>
            <y1>-245</y1>
            <x2>-1242</x2>
            <y2>-243</y2>
        </Foothold>
        <Foothold>
            <x1>-1242</x1>
            <y1>-243</y1>
            <x2>-1237</x2>
            <y2>-243</y2>
        </Foothold>
        <Foothold>
            <x1>-1237</x1>
            <y1>-243</y1>
            <x2>-1232</x2>
            <y2>-245</y2>
        </Foothold>
        <Foothold>
            <x1>-1232</x1>
            <y1>-245</y1>
            <x2>-1225</x2>
            <y2>-245</y2>
        </Foothold>
        <Foothold>
            <x1>-1225</x1>
            <y1>-245</y1>
            <x2>-1215</x2>
            <y2>-240</y2>
        </Foothold>
        <Foothold>
            <x1>-1335</x1>
            <y1>-210</y1>
            <x2>-1335</x2>
            <y2>-240</y2>
        </Foothold>
        <Foothold>
            <x1>-1335</x1>
            <y1>-240</y1>
            <x2>-1305</x2>
            <y2>-240</y2>
        </Foothold>
        <Foothold>
            <x1>-1335</x1>
            <y1>-90</y1>
            <x2>-1335</x2>
            <y2>-150</y2>
        </Foothold>
        <Foothold>
            <x1>-735</x1>
            <y1>-120</y1>
            <x2>-735</x2>
            <y2>-90</y2>
        </Foothold>
        <Foothold>
            <x1>-495</x1>
            <y1>-240</y1>
            <x2>-485</x2>
            <y2>-242</y2>
        </Foothold>
        <Foothold>
            <x1>-485</x1>
            <y1>-242</y1>
            <x2>-477</x2>
            <y2>-240</y2>
        </Foothold>
        <Foothold>
            <x1>-477</x1>
            <y1>-240</y1>
            <x2>-470</x2>
            <y2>-243</y2>
        </Foothold>
        <Foothold>
            <x1>-470</x1>
            <y1>-243</y1>
            <x2>-445</x2>
            <y2>-243</y2>
        </Foothold>
        <Foothold>
            <x1>-445</x1>
            <y1>-243</y1>
            <x2>-438</x2>
            <y2>-245</y2>
        </Foothold>
        <Foothold>
            <x1>-438</x1>
            <y1>-245</y1>
            <x2>-426</x2>
            <y2>-241</y2>
        </Foothold>
        <Foothold>
            <x1>-426</x1>
            <y1>-241</y1>
            <x2>-411</x2>
            <y2>-243</y2>
        </Foothold>
        <Foothold>
            <x1>-411</x1>
            <y1>-243</y1>
            <x2>-405</x2>
            <y2>-240</y2>
        </Foothold>
        <Foothold>
            <x1>-675</x1>
            <y1>-60</y1>
            <x2>-667</x2>
            <y2>-63</y2>
        </Foothold>
        <Foothold>
            <x1>-667</x1>
            <y1>-63</y1>
            <x2>-657</x2>
            <y2>-62</y2>
        </Foothold>
        <Foothold>
            <x1>-657</x1>
            <y1>-62</y1>
            <x2>-652</x2>
            <y2>-60</y2>
        </Foothold>
        <Foothold>
            <x1>-652</x1>
            <y1>-60</y1>
            <x2>-644</x2>
            <y2>-63</y2>
        </Foothold>
        <Foothold>
            <x1>-644</x1>
            <y1>-63</y1>
            <x2>-621</x2>
            <y2>-62</y2>
        </Foothold>
        <Foothold>
            <x1>-621</x1>
            <y1>-62</y1>
            <x2>-615</x2>
            <y2>-60</y2>
        </Foothold>
        <Foothold>
            <x1>-615</x1>
            <y1>-60</y1>
            <x2>-603</x2>
            <y2>-60</y2>
        </Foothold>
        <Foothold>
            <x1>-603</x1>
            <y1>-60</y1>
            <x2>-598</x2>
            <y2>-62</y2>
        </Foothold>
        <Foothold>
            <x1>-598</x1>
            <y1>-62</y1>
            <x2>-591</x2>
            <y2>-63</y2>
        </Foothold>
        <Foothold>
            <x1>-591</x1>
            <y1>-63</y1>
            <x2>-585</x2>
            <y2>-60</y2>
        </Foothold>
        <Foothold>
            <x1>-525</x1>
            <y1>-90</y1>
            <x2>-525</x2>
            <y2>-150</y2>
        </Foothold>
        <Foothold>
            <x1>-1335</x1>
            <y1>-30</y1>
            <x2>-1335</x2>
            <y2>-90</y2>
        </Foothold>
        <Foothold>
            <x1>-525</x1>
            <y1>-150</y1>
            <x2>-525</x2>
            <y2>-210</y2>
        </Foothold>
        <Foothold>
            <x1>-525</x1>
            <y1>-210</y1>
            <x2>-525</x2>
            <y2>-240</y2>
        </Foothold>
        <Foothold>
            <x1>-525</x1>
            <y1>-240</y1>
            <x2>-495</x2>
            <y2>-240</y2>
        </Foothold>
        <Foothold>
            <x1>-945</x1>
            <y1>-240</y1>
            <x2>-937</x2>
            <y2>-233</y2>
        </Foothold>
        <Foothold>
            <x1>-937</x1>
            <y1>-233</y1>
            <x2>-924</x2>
            <y2>-230</y2>
        </Foothold>
        <Foothold>
            <x1>-924</x1>
            <y1>-230</y1>
            <x2>-916</x2>
            <y2>-222</y2>
        </Foothold>
        <Foothold>
            <x1>-916</x1>
            <y1>-222</y1>
            <x2>-906</x2>
            <y2>-218</y2>
        </Foothold>
        <Foothold>
            <x1>-906</x1>
            <y1>-218</y1>
            <x2>-900</x2>
            <y2>-213</y2>
        </Foothold>
        <Foothold>
            <x1>-900</x1>
            <y1>-213</y1>
            <x2>-895</x2>
            <y2>-209</y2>
        </Foothold>
        <Foothold>
            <x1>-895</x1>
            <y1>-209</y1>
            <x2>-886</x2>
            <y2>-207</y2>
        </Foothold>
        <Foothold>
            <x1>-886</x1>
            <y1>-207</y1>
            <x2>-880</x2>
            <y2>-203</y2>
        </Foothold>
        <Foothold>
            <x1>-880</x1>
            <y1>-203</y1>
            <x2>-870</x2>
            <y2>-190</y2>
        </Foothold>
        <Foothold>
            <x1>-870</x1>
            <y1>-190</y1>
            <x2>-864</x2>
            <y2>-187</y2>
        </Foothold>
        <Foothold>
            <x1>-864</x1>
            <y1>-187</y1>
            <x2>-855</x2>
            <y2>-180</y2>
        </Foothold>
        <Foothold>
            <x1>-855</x1>
            <y1>-180</y1>
            <x2>-847</x2>
            <y2>-173</y2>
        </Foothold>
        <Foothold>
            <x1>-847</x1>
            <y1>-173</y1>
            <x2>-834</x2>
            <y2>-170</y2>
        </Foothold>
        <Foothold>
            <x1>-834</x1>
            <y1>-170</y1>
            <x2>-826</x2>
            <y2>-162</y2>
        </Foothold>
        <Foothold>
            <x1>-826</x1>
            <y1>-162</y1>
            <x2>-816</x2>
            <y2>-158</y2>
        </Foothold>
        <Foothold>
            <x1>-816</x1>
            <y1>-158</y1>
            <x2>-810</x2>
            <y2>-153</y2>
        </Foothold>
        <Foothold>
            <x1>-810</x1>
            <y1>-153</y1>
            <x2>-805</x2>
            <y2>-149</y2>
        </Foothold>
        <Foothold>
            <x1>-805</x1>
            <y1>-149</y1>
            <x2>-796</x2>
            <y2>-147</y2>
        </Foothold>
        <Foothold>
            <x1>-796</x1>
            <y1>-147</y1>
            <x2>-790</x2>
            <y2>-143</y2>
        </Foothold>
        <Foothold>
            <x1>-790</x1>
            <y1>-143</y1>
            <x2>-780</x2>
            <y2>-130</y2>
        </Foothold>
        <Foothold>
            <x1>-780</x1>
            <y1>-130</y1>
            <x2>-774</x2>
            <y2>-127</y2>
        </Foothold>
        <Foothold>
            <x1>-774</x1>
            <y1>-127</y1>
            <x2>-765</x2>
            <y2>-120</y2>
        </Foothold>
        <Foothold>
            <x1>-765</x1>
            <y1>-120</y1>
            <x2>-735</x2>
            <y2>-120</y2>
        </Foothold>
        <Foothold>
            <x1>-1125</x1>
            <y1>-240</y1>
            <x2>-1117</x2>
            <y2>-243</y2>
        </Foothold>
        <Foothold>
            <x1>-1117</x1>
            <y1>-243</y1>
            <x2>-1107</x2>
            <y2>-242</y2>
        </Foothold>
        <Foothold>
            <x1>-1107</x1>
            <y1>-242</y1>
            <x2>-1102</x2>
            <y2>-240</y2>
        </Foothold>
        <Foothold>
            <x1>-1102</x1>
            <y1>-240</y1>
            <x2>-1094</x2>
            <y2>-243</y2>
        </Foothold>
        <Foothold>
            <x1>-1094</x1>
            <y1>-243</y1>
            <x2>-1071</x2>
            <y2>-242</y2>
        </Foothold>
        <Foothold>
            <x1>-1071</x1>
            <y1>-242</y1>
            <x2>-1065</x2>
            <y2>-240</y2>
        </Foothold>
        <Foothold>
            <x1>-1065</x1>
            <y1>-240</y1>
            <x2>-1053</x2>
            <y2>-240</y2>
        </Foothold>
        <Foothold>
            <x1>-1053</x1>
            <y1>-240</y1>
            <x2>-1048</x2>
            <y2>-242</y2>
        </Foothold>
        <Foothold>
            <x1>-1048</x1>
            <y1>-242</y1>
            <x2>-1041</x2>
            <y2>-243</y2>
        </Foothold>
        <Foothold>
            <x1>-1041</x1>
            <y1>-243</y1>
            <x2>-1035</x2>
            <y2>-240</y2>
        </Foothold>
        <Foothold>
            <x1>-1035</x1>
            <y1>-240</y1>
            <x2>-1027</x2>
            <y2>-243</y2>
        </Foothold>
        <Foothold>
            <x1>-1027</x1>
            <y1>-243</y1>
            <x2>-1017</x2>
            <y2>-242</y2>
        </Foothold>
        <Foothold>
            <x1>-1017</x1>
            <y1>-242</y1>
            <x2>-1012</x2>
            <y2>-240</y2>
        </Foothold>
        <Foothold>
            <x1>-1012</x1>
            <y1>-240</y1>
            <x2>-1004</x2>
            <y2>-243</y2>
        </Foothold>
        <Foothold>
            <x1>-1004</x1>
            <y1>-243</y1>
            <x2>-981</x2>
            <y2>-242</y2>
        </Foothold>
        <Foothold>
            <x1>-981</x1>
            <y1>-242</y1>
            <x2>-975</x2>
            <y2>-240</y2>
        </Foothold>
        <Foothold>
            <x1>-975</x1>
            <y1>-240</y1>
            <x2>-963</x2>
            <y2>-240</y2>
        </Foothold>
        <Foothold>
            <x1>-963</x1>
            <y1>-240</y1>
            <x2>-958</x2>
            <y2>-242</y2>
        </Foothold>
        <Foothold>
            <x1>-958</x1>
            <y1>-242</y1>
            <x2>-951</x2>
            <y2>-243</y2>
        </Foothold>
        <Foothold>
            <x1>-951</x1>
            <y1>-243</y1>
            <x2>-945</x2>
            <y2>-240</y2>
        </Foothold>
        <Foothold>
            <x1>-585</x1>
            <y1>-60</y1>
            <x2>-577</x2>
            <y2>-63</y2>
        </Foothold>
        <Foothold>
            <x1>-577</x1>
            <y1>-63</y1>
            <x2>-566</x2>
            <y2>-63</y2>
        </Foothold>
        <Foothold>
            <x1>-566</x1>
            <y1>-63</y1>
            <x2>-556</x2>
            <y2>-67</y2>
        </Foothold>
        <Foothold>
            <x1>-556</x1>
            <y1>-67</y1>
            <x2>-547</x2>
            <y2>-67</y2>
        </Foothold>
        <Foothold>
            <x1>-547</x1>
            <y1>-67</y1>
            <x2>-538</x2>
            <y2>-63</y2>
        </Foothold>
        <Foothold>
            <x1>-538</x1>
            <y1>-63</y1>
            <x2>-528</x2>
            <y2>-65</y2>
        </Foothold>
        <Foothold>
            <x1>-528</x1>
            <y1>-65</y1>
            <x2>-525</x2>
            <y2>-64</y2>
        </Foothold>
        <Foothold>
            <x1>-525</x1>
            <y1>-64</y1>
            <x2>-525</x2>
            <y2>-90</y2>
        </Foothold>
        <Foothold>
            <x1>-735</x1>
            <y1>-90</y1>
            <x2>-735</x2>
            <y2>-63</y2>
        </Foothold>
        <Foothold>
            <x1>-735</x1>
            <y1>-63</y1>
            <x2>-729</x2>
            <y2>-62</y2>
        </Foothold>
        <Foothold>
            <x1>-315</x1>
            <y1>-240</y1>
            <x2>-305</x2>
            <y2>-242</y2>
        </Foothold>
        <Foothold>
            <x1>-305</x1>
            <y1>-242</y1>
            <x2>-297</x2>
            <y2>-240</y2>
        </Foothold>
        <Foothold>
            <x1>-297</x1>
            <y1>-240</y1>
            <x2>-290</x2>
            <y2>-243</y2>
        </Foothold>
        <Foothold>
            <x1>-290</x1>
            <y1>-243</y1>
            <x2>-265</x2>
            <y2>-243</y2>
        </Foothold>
        <Foothold>
            <x1>-265</x1>
            <y1>-243</y1>
            <x2>-258</x2>
            <y2>-245</y2>
        </Foothold>
        <Foothold>
            <x1>-258</x1>
            <y1>-245</y1>
            <x2>-246</x2>
            <y2>-241</y2>
        </Foothold>
        <Foothold>
            <x1>-246</x1>
            <y1>-241</y1>
            <x2>-231</x2>
            <y2>-243</y2>
        </Foothold>
        <Foothold>
            <x1>-231</x1>
            <y1>-243</y1>
            <x2>-225</x2>
            <y2>-240</y2>
        </Foothold>
        <Foothold>
            <x1>-1110</x1>
            <y1>-293</y1>
            <x2>-1099</x2>
            <y2>-283</y2>
        </Foothold>
        <Foothold>
            <x1>-1099</x1>
            <y1>-283</y1>
            <x2>-1077</x2>
            <y2>-281</y2>
        </Foothold>
        <Foothold>
            <x1>-1077</x1>
            <y1>-281</y1>
            <x2>-1064</x2>
            <y2>-289</y2>
        </Foothold>
        <Foothold>
            <x1>-1064</x1>
            <y1>-289</y1>
            <x2>-1059</x2>
            <y2>-299</y2>
        </Foothold>
        <Foothold>
            <x1>-1009</x1>
            <y1>-436</y1>
            <x2>-802</x2>
            <y2>-436</y2>
        </Foothold>
        <Foothold>
            <x1>-802</x1>
            <y1>-436</y1>
            <x2>-797</x2>
            <y2>-438</y2>
        </Foothold>
        <Foothold>
            <x1>-797</x1>
            <y1>-438</y1>
            <x2>-782</x2>
            <y2>-435</y2>
        </Foothold>
        <Foothold>
            <x1>-782</x1>
            <y1>-435</y1>
            <x2>-771</x2>
            <y2>-425</y2>
        </Foothold>
        <Foothold>
            <x1>-771</x1>
            <y1>-425</y1>
            <x2>-763</x2>
            <y2>-423</y2>
        </Foothold>
        <Foothold>
            <x1>-917</x1>
            <y1>-484</y1>
            <x2>-906</x2>
            <y2>-474</y2>
        </Foothold>
        <Foothold>
            <x1>-906</x1>
            <y1>-474</y1>
            <x2>-884</x2>
            <y2>-472</y2>
        </Foothold>
        <Foothold>
            <x1>-884</x1>
            <y1>-472</y1>
            <x2>-871</x2>
            <y2>-480</y2>
        </Foothold>
        <Foothold>
            <x1>-871</x1>
            <y1>-480</y1>
            <x2>-866</x2>
            <y2>-490</y2>
        </Foothold>
        <Foothold>
            <x1>-794</x1>
            <y1>-364</y1>
            <x2>-692</x2>
            <y2>-364</y2>
        </Foothold>
        <Foothold>
            <x1>-692</x1>
            <y1>-364</y1>
            <x2>-688</x2>
            <y2>-363</y2>
        </Foothold>
        <Foothold>
            <x1>-688</x1>
            <y1>-363</y1>
            <x2>-652</x2>
            <y2>-363</y2>
        </Foothold>
        <Foothold>
            <x1>-987</x1>
            <y1>-315</y1>
            <x2>-885</x2>
            <y2>-315</y2>
        </Foothold>
        <Foothold>
            <x1>-885</x1>
            <y1>-315</y1>
            <x2>-881</x2>
            <y2>-314</y2>
        </Foothold>
        <Foothold>
            <x1>-881</x1>
            <y1>-314</y1>
            <x2>-845</x2>
            <y2>-314</y2>
        </Foothold>
    </Footholds>
</Map>
